tpconfig/__init__.py
tpconfig/cdk_controller.py
tpconfig/config_manager.py
tpconfig-0.1.9.dist-info/METADATA
tpconfig-0.1.9.dist-info/WHEEL
tpconfig-0.1.9.dist-info/top_level.txt
tpconfig-0.1.9.dist-info/RECORD
